{
  "pluginId": "default",
  "version": "current",
  "label": "Next",
  "banner": null,
  "badge": false,
  "noIndex": false,
  "className": "docs-version-current",
  "isLast": true,
  "docsSidebars": {
    "docsSidebar": [
      {
        "type": "link",
        "label": "API Reference",
        "href": "/api-reference",
        "docId": "api-reference",
        "unlisted": false
      },
      {
        "type": "category",
        "label": "Architecture",
        "items": [
          {
            "type": "link",
            "label": "Backend Architecture & Conventions",
            "href": "/backend-architecture",
            "docId": "backend-architecture",
            "unlisted": false
          },
          {
            "type": "link",
            "label": "Frontend Architecture & Conventions",
            "href": "/frontend-architecture",
            "docId": "frontend-architecture",
            "unlisted": false
          }
        ],
        "collapsed": true,
        "collapsible": true
      },
      {
        "type": "category",
        "label": "API Documentation",
        "items": [
          {
            "type": "category",
            "label": "Core & Authentication",
            "items": [
              {
                "type": "link",
                "label": "API Reference: Authentication",
                "href": "/api/auth",
                "docId": "api/auth",
                "unlisted": false
              },
              {
                "type": "link",
                "label": "API Reference: OIDC Configuration",
                "href": "/api/oidc",
                "docId": "api/oidc",
                "unlisted": false
              },
              {
                "type": "link",
                "label": "API Reference: Organizations",
                "href": "/api/organizations",
                "docId": "api/organizations",
                "unlisted": false
              },
              {
                "type": "link",
                "label": "API Reference: Companies",
                "href": "/api/company",
                "docId": "api/company",
                "unlisted": false
              },
              {
                "type": "link",
                "label": "API Reference: Teams",
                "href": "/api/teams",
                "docId": "api/teams",
                "unlisted": false
              },
              {
                "type": "link",
                "label": "API Reference: Projects (Applications)",
                "href": "/api/projects",
                "docId": "api/projects",
                "unlisted": false
              },
              {
                "type": "link",
                "label": "API Reference: Memberships",
                "href": "/api/memberships",
                "docId": "api/memberships",
                "unlisted": false
              }
            ],
            "collapsed": true,
            "collapsible": true
          },
          {
            "type": "category",
            "label": "Supporting Resources",
            "items": [
              {
                "type": "link",
                "label": "API Reference: Invitations",
                "href": "/api/invitations",
                "docId": "api/invitations",
                "unlisted": false
              },
              {
                "type": "link",
                "label": "API Reference: SCM Integrations",
                "href": "/api/integrations",
                "docId": "api/integrations",
                "unlisted": false
              },
              {
                "type": "link",
                "label": "API Reference: Security Tools",
                "href": "/api/security-tools",
                "docId": "api/security-tools",
                "unlisted": false
              },
              {
                "type": "link",
                "label": "API Reference: Findings",
                "href": "/api/findings",
                "docId": "api/findings",
                "unlisted": false
              },
              {
                "type": "link",
                "label": "API Reference: Hierarchy",
                "href": "/api/hierarchy",
                "docId": "api/hierarchy",
                "unlisted": false
              },
              {
                "type": "link",
                "label": "API Reference: Relationships",
                "href": "/api/relationships",
                "docId": "api/relationships",
                "unlisted": false
              },
              {
                "type": "link",
                "label": "API Reference: Technologies",
                "href": "/api/technologies",
                "docId": "api/technologies",
                "unlisted": false
              }
            ],
            "collapsed": true,
            "collapsible": true
          }
        ],
        "collapsed": true,
        "collapsible": true
      },
      {
        "type": "category",
        "label": "Frontend Documentation",
        "items": [
          {
            "type": "link",
            "label": "Frontend Documentation: Lib Utilities",
            "href": "/frontend/lib",
            "docId": "frontend/lib",
            "unlisted": false
          },
          {
            "type": "link",
            "label": "Frontend Documentation: Custom Hooks",
            "href": "/frontend/hooks",
            "docId": "frontend/hooks",
            "unlisted": false
          },
          {
            "type": "link",
            "label": "Frontend Documentation: Pages",
            "href": "/frontend/pages",
            "docId": "frontend/pages",
            "unlisted": false
          },
          {
            "type": "category",
            "label": "Components",
            "items": [
              {
                "type": "link",
                "label": "Frontend Documentation: Application Components",
                "href": "/frontend/components/applications",
                "docId": "frontend/components/applications",
                "unlisted": false
              },
              {
                "type": "link",
                "label": "Frontend Documentation: Architecture Components",
                "href": "/frontend/components/architecture",
                "docId": "frontend/components/architecture",
                "unlisted": false
              },
              {
                "type": "link",
                "label": "Frontend Documentation: Findings Components",
                "href": "/frontend/components/findings",
                "docId": "frontend/components/findings",
                "unlisted": false
              },
              {
                "type": "link",
                "label": "Frontend Documentation: Integration Components",
                "href": "/frontend/components/integrations",
                "docId": "frontend/components/integrations",
                "unlisted": false
              },
              {
                "type": "link",
                "label": "Frontend Documentation: Settings Components",
                "href": "/frontend/components/settings",
                "docId": "frontend/components/settings",
                "unlisted": false
              },
              {
                "type": "link",
                "label": "Frontend Documentation: Sidebar Components",
                "href": "/frontend/components/sidebar",
                "docId": "frontend/components/sidebar",
                "unlisted": false
              }
            ],
            "collapsed": true,
            "collapsible": true
          },
          {
            "type": "category",
            "label": "Stores",
            "items": [
              {
                "type": "link",
                "label": "Store: useAuthStore",
                "href": "/frontend/stores/useAuthStore",
                "docId": "frontend/stores/useAuthStore",
                "unlisted": false
              },
              {
                "type": "link",
                "label": "Store: useArchitectureStore",
                "href": "/frontend/stores/useArchitectureStore",
                "docId": "frontend/stores/useArchitectureStore",
                "unlisted": false
              },
              {
                "type": "link",
                "label": "Store: useCompanyStore",
                "href": "/frontend/stores/useCompanyStore",
                "docId": "frontend/stores/useCompanyStore",
                "unlisted": false
              },
              {
                "type": "link",
                "label": "Store: useDomainStore",
                "href": "/frontend/stores/useDomainStore",
                "docId": "frontend/stores/useDomainStore",
                "unlisted": false
              },
              {
                "type": "link",
                "label": "Store: useFindingStore",
                "href": "/frontend/stores/useFindingStore",
                "docId": "frontend/stores/useFindingStore",
                "unlisted": false
              },
              {
                "type": "link",
                "label": "Store: useHierarchyStore",
                "href": "/frontend/stores/useHierarchyStore",
                "docId": "frontend/stores/useHierarchyStore",
                "unlisted": false
              },
              {
                "type": "link",
                "label": "Store: useIntegrationStore",
                "href": "/frontend/stores/useIntegrationStore",
                "docId": "frontend/stores/useIntegrationStore",
                "unlisted": false
              },
              {
                "type": "link",
                "label": "Store: useMembershipStore",
                "href": "/frontend/stores/useMembershipStore",
                "docId": "frontend/stores/useMembershipStore",
                "unlisted": false
              },
              {
                "type": "link",
                "label": "Store: useOIDCStore",
                "href": "/frontend/stores/useOIDCStore",
                "docId": "frontend/stores/useOIDCStore",
                "unlisted": false
              },
              {
                "type": "link",
                "label": "Store: useOrganizationStore",
                "href": "/frontend/stores/useOrganizationStore",
                "docId": "frontend/stores/useOrganizationStore",
                "unlisted": false
              },
              {
                "type": "link",
                "label": "Store: useProjectStore",
                "href": "/frontend/stores/useProjectStore",
                "docId": "frontend/stores/useProjectStore",
                "unlisted": false
              },
              {
                "type": "link",
                "label": "Store: useTeamStore",
                "href": "/frontend/stores/useTeamStore",
                "docId": "frontend/stores/useTeamStore",
                "unlisted": false
              },
              {
                "type": "link",
                "label": "Store: useUIStore",
                "href": "/frontend/stores/useUIStore",
                "docId": "frontend/stores/useUIStore",
                "unlisted": false
              }
            ],
            "collapsed": true,
            "collapsible": true
          }
        ],
        "collapsed": true,
        "collapsible": true
      }
    ]
  },
  "docs": {
    "api-reference": {
      "id": "api-reference",
      "title": "API Reference",
      "description": "This document serves as a high-level table of contents for the Stagehand backend API. The API is organized by resource, with each major resource having its own detailed documentation file.",
      "sidebar": "docsSidebar"
    },
    "api/auth": {
      "id": "api/auth",
      "title": "API Reference: Authentication",
      "description": "This document provides a detailed breakdown of the authentication-related API endpoints.",
      "sidebar": "docsSidebar"
    },
    "api/company": {
      "id": "api/company",
      "title": "API Reference: Companies",
      "description": "This document provides a detailed breakdown of the company-related API endpoints.",
      "sidebar": "docsSidebar"
    },
    "api/findings": {
      "id": "api/findings",
      "title": "API Reference: Findings",
      "description": "This document provides a detailed breakdown of the security finding-related API endpoints.",
      "sidebar": "docsSidebar"
    },
    "api/hierarchy": {
      "id": "api/hierarchy",
      "title": "API Reference: Hierarchy",
      "description": "This document provides a detailed breakdown of the hierarchy-related API endpoints.",
      "sidebar": "docsSidebar"
    },
    "api/integrations": {
      "id": "api/integrations",
      "title": "API Reference: SCM Integrations",
      "description": "This document provides a detailed breakdown of the Source Code Management (SCM) integration API endpoints.",
      "sidebar": "docsSidebar"
    },
    "api/invitations": {
      "id": "api/invitations",
      "title": "API Reference: Invitations",
      "description": "This document provides a detailed breakdown of the invitation-related API endpoints.",
      "sidebar": "docsSidebar"
    },
    "api/memberships": {
      "id": "api/memberships",
      "title": "API Reference: Memberships",
      "description": "This document provides a detailed breakdown of the membership-related API endpoints.",
      "sidebar": "docsSidebar"
    },
    "api/oidc": {
      "id": "api/oidc",
      "title": "API Reference: OIDC Configuration",
      "description": "This document provides a detailed breakdown of the OIDC configuration-related API endpoints.",
      "sidebar": "docsSidebar"
    },
    "api/organizations": {
      "id": "api/organizations",
      "title": "API Reference: Organizations",
      "description": "This document provides a detailed breakdown of the organization-related API endpoints.",
      "sidebar": "docsSidebar"
    },
    "api/projects": {
      "id": "api/projects",
      "title": "API Reference: Projects (Applications)",
      "description": "This document provides a detailed breakdown of the project-related API endpoints. \"Projects\" are the core entities in the Stagehand developer catalog and are often referred to as \"Applications\" in the UI and business logic.",
      "sidebar": "docsSidebar"
    },
    "api/relationships": {
      "id": "api/relationships",
      "title": "API Reference: Relationships",
      "description": "This document provides a detailed breakdown of the project relationship-related API endpoints.",
      "sidebar": "docsSidebar"
    },
    "api/security-tools": {
      "id": "api/security-tools",
      "title": "API Reference: Security Tools",
      "description": "This document provides a detailed breakdown of the security tool integration-related API endpoints.",
      "sidebar": "docsSidebar"
    },
    "api/teams": {
      "id": "api/teams",
      "title": "API Reference: Teams",
      "description": "This document provides a detailed breakdown of the team-related API endpoints.",
      "sidebar": "docsSidebar"
    },
    "api/technologies": {
      "id": "api/technologies",
      "title": "API Reference: Technologies",
      "description": "This document provides a detailed breakdown of the technology-related API endpoints.",
      "sidebar": "docsSidebar"
    },
    "backend-architecture": {
      "id": "backend-architecture",
      "title": "Backend Architecture & Conventions",
      "description": "This document provides a detailed guide to the structure, conventions, and patterns used in the packages/api service. It is intended for developers working on the backend to ensure consistency and maintainability.",
      "sidebar": "docsSidebar"
    },
    "frontend-architecture": {
      "id": "frontend-architecture",
      "title": "Frontend Architecture & Conventions",
      "description": "This document provides a detailed guide to the structure, conventions, and patterns used in the packages/web service. It is intended for developers working on the frontend to ensure consistency and maintainability.",
      "sidebar": "docsSidebar"
    },
    "frontend/components/applications": {
      "id": "frontend/components/applications",
      "title": "Frontend Documentation: Application Components",
      "description": "This document provides a breakdown of the components used for displaying the details of a single application (referred to as a \"Project\" in the backend and hierarchy).",
      "sidebar": "docsSidebar"
    },
    "frontend/components/architecture": {
      "id": "frontend/components/architecture",
      "title": "Frontend Documentation: Architecture Components",
      "description": "This document provides a breakdown of the components used for rendering the project dependency graph.",
      "sidebar": "docsSidebar"
    },
    "frontend/components/findings": {
      "id": "frontend/components/findings",
      "title": "Frontend Documentation: Findings Components",
      "description": "This document provides a breakdown of the components used for displaying security findings.",
      "sidebar": "docsSidebar"
    },
    "frontend/components/integrations": {
      "id": "frontend/components/integrations",
      "title": "Frontend Documentation: Integration Components",
      "description": "This document provides a breakdown of the components used for managing integrations with external tools like GitHub (SCM) and Snyk (Security Tools).",
      "sidebar": "docsSidebar"
    },
    "frontend/components/settings": {
      "id": "frontend/components/settings",
      "title": "Frontend Documentation: Settings Components",
      "description": "This document provides a breakdown of the components used within the SettingsPage.",
      "sidebar": "docsSidebar"
    },
    "frontend/components/sidebar": {
      "id": "frontend/components/sidebar",
      "title": "Frontend Documentation: Sidebar Components",
      "description": "This document provides a breakdown of the components that make up the main navigation sidebar.",
      "sidebar": "docsSidebar"
    },
    "frontend/hooks": {
      "id": "frontend/hooks",
      "title": "Frontend Documentation: Custom Hooks",
      "description": "This document provides a breakdown of the custom React hooks used throughout the application.",
      "sidebar": "docsSidebar"
    },
    "frontend/lib": {
      "id": "frontend/lib",
      "title": "Frontend Documentation: Lib Utilities",
      "description": "This document provides a breakdown of the shared utility functions and constants defined in the lib directory.",
      "sidebar": "docsSidebar"
    },
    "frontend/pages": {
      "id": "frontend/pages",
      "title": "Frontend Documentation: Pages",
      "description": "This document provides an in-depth breakdown of the main \"page\" components, detailing their display function and the specific state they consume.",
      "sidebar": "docsSidebar"
    },
    "frontend/stores/useArchitectureStore": {
      "id": "frontend/stores/useArchitectureStore",
      "title": "Store: useArchitectureStore",
      "description": "File:* packages/web/src/stores/useArchitectureStore.js",
      "sidebar": "docsSidebar"
    },
    "frontend/stores/useAuthStore": {
      "id": "frontend/stores/useAuthStore",
      "title": "Store: useAuthStore",
      "description": "File:* packages/web/src/stores/useAuthStore.js",
      "sidebar": "docsSidebar"
    },
    "frontend/stores/useCompanyStore": {
      "id": "frontend/stores/useCompanyStore",
      "title": "Store: useCompanyStore",
      "description": "File:* packages/web/src/stores/useCompanyStore.js",
      "sidebar": "docsSidebar"
    },
    "frontend/stores/useDomainStore": {
      "id": "frontend/stores/useDomainStore",
      "title": "Store: useDomainStore",
      "description": "File:* packages/web/src/stores/useDomainStore.js",
      "sidebar": "docsSidebar"
    },
    "frontend/stores/useFindingStore": {
      "id": "frontend/stores/useFindingStore",
      "title": "Store: useFindingStore",
      "description": "File:* packages/web/src/stores/useFindingStore.js",
      "sidebar": "docsSidebar"
    },
    "frontend/stores/useHierarchyStore": {
      "id": "frontend/stores/useHierarchyStore",
      "title": "Store: useHierarchyStore",
      "description": "File:* packages/web/src/stores/useHierarchyStore.js",
      "sidebar": "docsSidebar"
    },
    "frontend/stores/useIntegrationStore": {
      "id": "frontend/stores/useIntegrationStore",
      "title": "Store: useIntegrationStore",
      "description": "File:* packages/web/src/stores/useIntegrationStore.js",
      "sidebar": "docsSidebar"
    },
    "frontend/stores/useMembershipStore": {
      "id": "frontend/stores/useMembershipStore",
      "title": "Store: useMembershipStore",
      "description": "File:* packages/web/src/stores/useMembershipStore.js",
      "sidebar": "docsSidebar"
    },
    "frontend/stores/useOIDCStore": {
      "id": "frontend/stores/useOIDCStore",
      "title": "Store: useOIDCStore",
      "description": "File:* packages/web/src/stores/useOIDCStore.js",
      "sidebar": "docsSidebar"
    },
    "frontend/stores/useOrganizationStore": {
      "id": "frontend/stores/useOrganizationStore",
      "title": "Store: useOrganizationStore",
      "description": "File:* packages/web/src/stores/useOrganizationStore.js",
      "sidebar": "docsSidebar"
    },
    "frontend/stores/useProjectStore": {
      "id": "frontend/stores/useProjectStore",
      "title": "Store: useProjectStore",
      "description": "File:* packages/web/src/stores/useProjectStore.js",
      "sidebar": "docsSidebar"
    },
    "frontend/stores/useTeamStore": {
      "id": "frontend/stores/useTeamStore",
      "title": "Store: useTeamStore",
      "description": "File:* packages/web/src/stores/useTeamStore.js",
      "sidebar": "docsSidebar"
    },
    "frontend/stores/useUIStore": {
      "id": "frontend/stores/useUIStore",
      "title": "Store: useUIStore",
      "description": "File:* packages/web/src/stores/useUIStore.js",
      "sidebar": "docsSidebar"
    },
    "index": {
      "id": "index",
      "title": "Stagehand Developer Documentation",
      "description": "Welcome to the comprehensive developer documentation for the Stagehand platform. This documentation covers everything from API references to architectural decisions, frontend components, and integration guides."
    }
  }
}